pyRKIntegrator/RungeKutta.py
pyRKIntegrator/RungeKutta.pyx
pyRKIntegrator/__init__.py
pyRKIntegrator/src/c/RK.c
pyRKIntegrator/src/c/RK.h
pyRKIntegrator/src/cpp/RK.cpp
pyRKIntegrator/src/cpp/RK.h
pyrkintegrator-2.2.1.dist-info/licenses/LICENSE
pyrkintegrator-2.2.1.dist-info/METADATA
pyrkintegrator-2.2.1.dist-info/WHEEL
pyrkintegrator-2.2.1.dist-info/top_level.txt
pyrkintegrator-2.2.1.dist-info/RECORD
