Metadata-Version: 2.4
Name: pyRKIntegrator
Version: 2.2.1
Summary: Adaptive generic Runge-Kutta and Runge-Kutta-Nystrom integrators developed in C++, with a Python interface
Home-page: https://github.com/ArnauMiro/pyRKIntegrator.git
Author: ['Arnau Miro', 'Manel Soria']
Author-email: Arnau Miro <arnau.miro@upc.edu>, Manel Soria <manel.soria@upc.edu>
Maintainer: Arnau Miro
Maintainer-email: Arnau Miro <arnau.miro@upc.edu>
License: GNU GENERAL PUBLIC LICENSE
Project-URL: Homepage, https://github.com/ArnauMiro/pyRKIntegrator
Project-URL: Bug Reports, https://github.com/ArnauMiro/pyRKIntegrator/issues
Project-URL: Source, https://github.com/ArnauMiro/pyRKIntegrator
Keywords: integrators,Runge-Kutta,Runge-Kutta-Nystrom
Classifier: Development Status :: 5 - Production/Stable
Classifier: Intended Audience :: Science/Research
Classifier: Topic :: Scientific/Engineering
Classifier: License :: OSI Approved :: GNU General Public License v3 (GPLv3)
Classifier: Programming Language :: Python :: 3
Classifier: Programming Language :: Python :: 3.7
Classifier: Programming Language :: Python :: 3.8
Classifier: Programming Language :: Python :: 3.9
Classifier: Programming Language :: Python :: 3.10
Classifier: Programming Language :: Python :: 3.11
Classifier: Programming Language :: Python :: 3 :: Only
Requires-Python: >=3.7
License-File: LICENSE
Requires-Dist: numpy
Requires-Dist: cython
Requires-Dist: matplotlib
Provides-Extra: full
Dynamic: author
Dynamic: home-page
Dynamic: license-file
Dynamic: maintainer
